pyVHACD.cpython-36m-x86_64-linux-gnu.so
pyVHACD-0.0.2.dist-info/RECORD
pyVHACD-0.0.2.dist-info/WHEEL
pyVHACD-0.0.2.dist-info/top_level.txt
pyVHACD-0.0.2.dist-info/LICENSE
pyVHACD-0.0.2.dist-info/METADATA
